three_layer_decryption.v
module three_layer_decryption(
    input [7:0] encrypted_data,
    input wire clk,
    input wire rst_n,
    output wire [7:0] decrypted_data
);

reg [7:0] inverted_bits;
reg [7:0] grey_code;
reg [7:0] circular_shifted;

// First layer: Inverting all the bits
always @(posedge clk or negedge rst_n) begin
    if (~rst_n) begin
        inverted_bits <= 8'b00000000; // Reset to zero on active-low reset
    end else begin
        inverted_bits <= ~encrypted_data;
    end
end

// Second layer: Conversion from Grey code
always @(posedge clk or negedge rst_n) begin
    if (~rst_n) begin
        grey_code <= 8'b00000000; // Reset to zero on active-low reset
    end else begin
        grey_code[0] <= inverted_bits[0];
        grey_code[1] <= inverted_bits[1] ^ grey_code[0];
        grey_code[2] <= inverted_bits[2] ^ grey_code[1];
        grey_code[3] <= inverted_bits[3] ^ grey_code[2];
        grey_code[4] <= inverted_bits[4] ^ grey_code[3];
        grey_code[5] <= inverted_bits[5] ^ grey_code[4];
        grey_code[6] <= inverted_bits[6] ^ grey_code[5];
        grey_code[7] <= inverted_bits[7] ^ grey_code[6];
    end
end

// Third layer: Circular right shift
always @(posedge clk or negedge rst_n) begin
    if (~rst_n) begin
        circular_shifted <= 8'b00000000; // Reset to zero on active-low reset
    end else begin
        circular_shifted <= {grey_code[0], grey_code[7:1]}; // Right circular shift
    end
end

// Output the result of the three layers
assign decrypted_data = circular_shifted;

endmodule

three_layer_encryption.v
module three_layer_encryption(
    input [7:0] in_data,
    input wire clk,
    input wire rst_n,
    output reg [7:0] encrypted_data
);

reg [7:0] circular_shifted;
reg [7:0] grey_code;
reg [7:0] inverted_bits;

// First layer: Circular right shift
always @(posedge clk or negedge rst_n) begin
    if (~rst_n) begin
        circular_shifted <= 8'b00000000; // Reset to zero on active-low reset
    end else begin
        circular_shifted <= {in_data[0], in_data[7:1]}; // Right circular shift
    end
end

// Second layer: Conversion to Grey code
always @(posedge clk or negedge rst_n) begin
    if (~rst_n) begin
        grey_code <= 8'b00000000; // Reset to zero on active-low reset
    end else begin
        grey_code[0] <= circular_shifted[0];
        grey_code[1] <= circular_shifted[1] ^ circular_shifted[0];
        grey_code[2] <= circular_shifted[2] ^ circular_shifted[1];
        grey_code[3] <= circular_shifted[3] ^ circular_shifted[2];
        grey_code[4] <= circular_shifted[4] ^ circular_shifted[3];
        grey_code[5] <= circular_shifted[5] ^ circular_shifted[4];
        grey_code[6] <= circular_shifted[6] ^ circular_shifted[5];
        grey_code[7] <= circular_shifted[7] ^ circular_shifted[6];
    end
end

// Third layer: Inverting all the bits
always @(posedge clk or negedge rst_n) begin
    if (~rst_n) begin
        inverted_bits <= 8'b00000000; // Reset to zero on active-low reset
    end else begin
        inverted_bits <= ~grey_code;
    end
end

// Output the result of the three layers
always @* begin
    encrypted_data = inverted_bits;
end

endmodule

three_layer_encryption_decryption_tb.v
`timescale 1ns/1ns
`include "three_layer_encryption.v"
`include "three_layer_decryption.v"

module three_layer_encryption_decryption_tb;

reg clk;
reg rst_n;
reg [7:0] in_data;
reg select;

wire [7:0] encrypted_data;
wire [7:0] decrypted_data;

// Instantiate encryption and decryption modules
three_layer_encryption u_encryptor (
    in_data,
    clk,
    rst_n,
    encrypted_data
);

three_layer_decryption u_decryptor (
    encrypted_data,
    clk,
    rst_n,
    decrypted_data
);

// Clock generation
initial begin
    $dumpfile("waveforms.vcd");
    $dumpvars(0, three_layer_encryption_decryption_tb.u_encryptor, three_layer_encryption_decryption_tb.u_decryptor);

    clk = 0;
    forever #5 clk = ~clk;
end

// Stimulus generation
initial begin
    rst_n = 0;
    in_data = 8'b11000101;
    select = 0;

    // Apply reset and wait for a few cycles
    #10 rst_n = 1;

    // Perform encryption and decryption with select input control
    #50 select = 0; // Display encrypted waveform only
    #100 select = 1; // Display both encrypted and decrypted waveforms
    #50 $finish;
end

// Multiplexer to select waveform for display
always @(posedge clk) begin
    if (select == 0) begin
        $display("Encrypted Data: %b", encrypted_data);
    end else begin
        $display("Encrypted Data: %b, Decrypted Data: %b", encrypted_data, decrypted_data);
    end
end

endmodule

waveforms.vcd
$date
	Tue Nov 14 11:26:24 2023
$end
$version
	Icarus Verilog
$end
$timescale
	1ns
$end
$scope module three_layer_encryption_decryption_tb $end
$scope module u_encryptor $end
$var wire 1 ! clk $end
$var wire 8 " in_data [7:0] $end
$var wire 1 # rst_n $end
$var reg 8 $ circular_shifted [7:0] $end
$var reg 8 % encrypted_data [7:0] $end
$var reg 8 & grey_code [7:0] $end
$var reg 8 ' inverted_bits [7:0] $end
$upscope $end
$upscope $end
$scope module three_layer_encryption_decryption_tb $end
$scope module u_decryptor $end
$var wire 1 ! clk $end
$var wire 8 ( decrypted_data [7:0] $end
$var wire 1 # rst_n $end
$var wire 8 ) encrypted_data [7:0] $end
$var reg 8 * circular_shifted [7:0] $end
$var reg 8 + grey_code [7:0] $end
$var reg 8 , inverted_bits [7:0] $end
$upscope $end
$upscope $end
$enddefinitions $end
#0
$dumpvars
b0 ,
b0 +
b0 *
b0 )
b0 (
b0 '
b0 &
b0 %
b0 $
0#
b11000101 "
0!
$end
#5
1!
#10
0!
1#
#15
b11111111 %
b11111111 )
b11100010 $
b11111111 '
b11111111 ,
1!
#20
0!
#25
b11111111 +
b0 ,
b100110 &
1!
#30
0!
#35
b11011001 %
b11011001 )
b11011001 '
b11111110 +
b11111111 (
b11111111 *
1!
#40
0!
#45
b1111111 (
b1111111 *
b11111100 +
b100110 ,
1!
#50
0!
#55
b11011110 +
b1111110 (
b1111110 *
1!
#60
0!
#65
b1101111 (
b1101111 *
b10011010 +
1!
#70
0!
#75
b10010 +
b1001101 (
b1001101 *
1!
#80
0!
#85
b1001 (
b1001 *
b10 +
1!
#90
0!
#95
b100010 +
b1 (
b1 *
1!
#100
0!
#105
b10001 (
b10001 *
b1100010 +
1!
#110
0!
#115
b11100010 +
b110001 (
b110001 *
1!
#120
0!
#125
b1110001 (
b1110001 *
1!
